nti/__init__.py
nti/transactions/__init__.py
nti/transactions/_httpexceptions.py
nti/transactions/_loglevels.py
nti/transactions/configure.zcml
nti/transactions/interfaces.py
nti/transactions/loop.py
nti/transactions/manager.py
nti/transactions/pyramid_tween.py
nti/transactions/queue.py
nti/transactions/transactions.py
nti/transactions/tests/__init__.py
nti/transactions/tests/test_loop.py
nti/transactions/tests/test_manager.py
nti/transactions/tests/test_pyramid_tween.py
nti/transactions/tests/test_queue.py
nti/transactions/tests/test_transactions.py
nti.transactions-5.1.0.dist-info/LICENSE
nti.transactions-5.1.0.dist-info/METADATA
nti.transactions-5.1.0.dist-info/WHEEL
nti.transactions-5.1.0.dist-info/top_level.txt
nti.transactions-5.1.0.dist-info/zip-safe
nti.transactions-5.1.0.dist-info/RECORD
