Metadata-Version: 2.1
Name: nti.transactions
Version: 5.1.0
Summary: NTI Transactions Utility
Home-page: https://github.com/OpenNTI/nti.transactions
Author: Jason Madden
Author-email: jason@nextthought.com
License: Apache
Keywords: ZODB transaction
Classifier: Intended Audience :: Developers
Classifier: Natural Language :: English
Classifier: Operating System :: OS Independent
Classifier: Development Status :: 5 - Production/Stable
Classifier: License :: OSI Approved :: Apache Software License
Classifier: Programming Language :: Python :: 3
Classifier: Programming Language :: Python :: 3 :: Only
Classifier: Programming Language :: Python :: 3.10
Classifier: Programming Language :: Python :: 3.11
Classifier: Programming Language :: Python :: 3.12
Classifier: Programming Language :: Python :: 3.13
Classifier: Programming Language :: Python :: Implementation :: CPython
Classifier: Programming Language :: Python :: Implementation :: PyPy
Classifier: Framework :: ZODB
Requires-Python: >=3.10
License-File: LICENSE
Requires-Dist: six
Requires-Dist: perfmetrics
Requires-Dist: transaction>=3.0.0
Requires-Dist: zope.cachedescriptors
Requires-Dist: zope.exceptions
Requires-Dist: zope.interface
Requires-Dist: zope.event
Provides-Extra: docs
Requires-Dist: Sphinx; extra == "docs"
Requires-Dist: repoze.sphinx.autointerface; extra == "docs"
Requires-Dist: pyhamcrest; extra == "docs"
Requires-Dist: sphinx-rtd-theme; python_version < "3.6" and extra == "docs"
Requires-Dist: furo; python_version >= "3.6" and extra == "docs"
Provides-Extra: gevent
Requires-Dist: gevent; extra == "gevent"
Provides-Extra: pyramid
Requires-Dist: pyramid>=1.2; extra == "pyramid"
Provides-Extra: test
Requires-Dist: coverage; extra == "test"
Requires-Dist: nti.testing; extra == "test"
Requires-Dist: pylint; extra == "test"
Requires-Dist: pyramid; extra == "test"
Requires-Dist: zope.component; extra == "test"
Requires-Dist: zope.testrunner; extra == "test"
Requires-Dist: ZODB; extra == "test"
